AUTHORS.rst
CONTRIBUTING.rst
HISTORY.rst
LICENSE
MANIFEST.in
README.rst
setup.cfg
setup.py
docs/Makefile
docs/authors.rst
docs/conf.py
docs/contributing.rst
docs/history.rst
docs/index.rst
docs/installation.rst
docs/make.bat
docs/readme.rst
docs/usage.rst
ocpexplore/__init__.py
ocpexplore/cli.py
ocpexplore/ocpexplore.py
ocpexplore.egg-info/PKG-INFO
ocpexplore.egg-info/SOURCES.txt
ocpexplore.egg-info/dependency_links.txt
ocpexplore.egg-info/entry_points.txt
ocpexplore.egg-info/not-zip-safe
ocpexplore.egg-info/requires.txt
ocpexplore.egg-info/top_level.txt
tests/__init__.py
tests/test_ocpexplore.py